SPI_master/rtl/top.v
module master(
	input wire clk,
	input wire rst_n,
	input wire start,
	input wire miso,
	input wire [7:0] data_in,
	output reg mosi,
	output reg sck,
	output reg cs,
	output reg [7:0] data_out,
	output reg done
);

localparam IDLE = 2'b00;
localparam START = 2'b01;
localparam TRANSFER = 2'b10;
localparam DONE = 2'b11;

reg [1:0] state, next_state;
reg [3:0] bit_cnt; // counting bits transmited.
reg [7:0] shift_reg; // Register for the bit translation.
reg shift_sck; // Used to create the signal SCK

// Defining the next state.
always @(posedge clk or negedge rst_n) begin
	if (!rst_n) begin
		state <= IDLE;
	end else begin
		state <= next_state;
	end
end

// FSM logic to control the SPI signals
always @(*) begin
	case(state)
		IDLE: begin
			if(start) begin
				next_state <= START; // transfer to the START state when the start signal is 1
			end else begin
				next_state <= IDLE;
			end
		end
		START: next_state <= TRANSFER; // after setuping before transfer to the TRANSFER state
		TRANSFER: begin
			if(bit_cnt == 4'b1001 && shift_sck) begin
				next_state <= DONE; // When the 8 bits are transmited , transfer to the DONE state
			end else begin
				next_state <= TRANSFER; // continue to transmit datas.
			end
		end
		DONE: next_state <= IDLE; // after communication, return to the IDLE state.
		default: next_state <= IDLE;
	endcase
end

// Logic to create the SPI signal
always @(posedge clk or negedge rst_n) begin
	if(!rst_n) begin
		mosi <= 1'b0;
		sck <= 1'b0;
		cs <= 1'b1;
		data_out <= 8'h00;
		done <= 1'b0;
		bit_cnt <= 4'b0;
		shift_reg <= 8'h00;
		shift_sck <= 1'b0;
	end else begin
		case(state)
			IDLE: begin
				cs <= 1'b1; // cancel activate cs when the state is IDLE.
				done <= 1'b0;
				sck <= 1'b0;
				shift_sck <= 1'b0;
				data_out <= 8'h00;
			end
			START: begin
				cs <= 1'b0;
				shift_reg <= data_in; // setup data need to send
				bit_cnt <= 4'b000;
				done <= 1'b0;
			end
			TRANSFER: begin
				shift_sck = ~shift_sck; // generate SCK clock pulse
				sck <= shift_sck;
				if(shift_sck) begin
					mosi <= shift_reg[7];
					shift_reg <= {shift_reg[6:0],1'b0};
					bit_cnt <= bit_cnt + 1'b1;
					if (bit_cnt < 9) begin
						data_out <= {data_out[6:0],miso};
					end
				end
			end
			DONE: begin
				cs <= 1'b1;
				done <= 1'b1;
			end
			default: begin
				cs <= 1'b1;
				done <= 1'b0;
			end
		endcase
	end
end
endmodule

SPI_master/tb/test_bench.v
`timescale 1ns/1ps
module test_bench;
	reg clk;
	reg rst_n;
	reg start;
	reg miso;
	reg [7:0] data_in;
	wire mosi;
	wire sck;
	wire cs;
	wire [7:0] data_out;
	wire done;

reg [7:0] exp_data;

	master dut(
		.clk(clk),
		.rst_n(rst_n),
		.start(start),
		.miso(miso),
		.data_in(data_in),
		.mosi(mosi),
		.sck(sck),
		.cs(cs),
		.data_out(data_out),
		.done(done)
	);

	initial begin
		clk = 0;
		forever #5 clk = ~clk;
	end

	task verify;
		input [7:0] sent_data;
		input [7:0] received_data;
		begin
			$display("At time: %t, rst_n = 1'b%b, start = 1'b%b", $time, rst_n, start);
			if( sent_data == received_data) begin
				$display("---------------------------------------------------------------------------------------------------------------");
				$display("PASSED: Sent data: 8'h%h, Received_data: 8'h%h",sent_data, received_data);
				$display("---------------------------------------------------------------------------------------------------------------");
			end else begin
				$display("---------------------------------------------------------------------------------------------------------------");
				$display("FAILED: Sent data: 8'h%h, Received_data: 8'h%h",sent_data, received_data);
				$display("---------------------------------------------------------------------------------------------------------------");
			end
		end
	endtask

	initial begin
		$dumpfile("test_bench.vcd");
		$dumpvars(0, test_bench);
		
		$display("------------------------------------------------------------------------------------------------------------------");	
		$display("----------------------------TESTBENCH FOR SPI MASTER--------------------------------------------------------------");
		$display("------------------------------------------------------------------------------------------------------------------");	

		rst_n = 0;
		start = 0;
		miso = 0;
		data_in = 0;
		@(posedge clk);
		verify(8'h00, 8'h00);

		rst_n = 1;
		@(posedge clk);
		data_in = 8'hf0;
		exp_data = data_in;
		start = 1;
		@(posedge clk);
		start = 0;
		wait(done);
		@(posedge clk);
		verify(exp_data, data_out);

		data_in = 8'h55;
		exp_data = data_in;
		start = 1;
		@(posedge clk);
		start = 0;
		wait(done);
		@(posedge clk);
		verify(exp_data, data_out);

		data_in = 8'haa;
		exp_data = 8'h00;
		@(posedge clk);
		verify(exp_data, data_out);
		
		data_in = 8'h78;
		exp_data = data_in;
		start = 1;
		@(posedge clk);
		start = 0;
		wait(done);
		@(posedge clk);
		verify(exp_data, data_out);
		
		data_in = 8'h33;
		exp_data = data_in;
		start = 1;
		@(posedge clk);
		start = 0;
		wait(done);
		@(posedge clk);
		verify(exp_data, data_out);

		#200;
		$finish;
		
	end

	// Simulate miso data
	always @(posedge dut.sck) begin
    		if (!dut.cs) begin
        	miso <= dut.mosi; // Echo mosi back to miso for test
   	end
end
endmodule

SPI_master/sim/test_bench.vcd
$date
	Mon Jan 13 14:28:11 2025
$end
$version
	Icarus Verilog
$end
$timescale
	1ps
$end
$scope module test_bench $end
$var wire 1 ! sck $end
$var wire 1 " mosi $end
$var wire 1 # done $end
$var wire 8 $ data_out [7:0] $end
$var wire 1 % cs $end
$var reg 1 & clk $end
$var reg 8 ' data_in [7:0] $end
$var reg 8 ( exp_data [7:0] $end
$var reg 1 ) miso $end
$var reg 1 * rst_n $end
$var reg 1 + start $end
$scope module dut $end
$var wire 1 & clk $end
$var wire 8 , data_in [7:0] $end
$var wire 1 ) miso $end
$var wire 1 * rst_n $end
$var wire 1 + start $end
$var parameter 2 - DONE $end
$var parameter 2 . IDLE $end
$var parameter 2 / START $end
$var parameter 2 0 TRANSFER $end
$var reg 4 1 bit_cnt [3:0] $end
$var reg 1 % cs $end
$var reg 8 2 data_out [7:0] $end
$var reg 1 # done $end
$var reg 1 " mosi $end
$var reg 2 3 next_state [1:0] $end
$var reg 1 ! sck $end
$var reg 8 4 shift_reg [7:0] $end
$var reg 1 5 shift_sck $end
$var reg 2 6 state [1:0] $end
$upscope $end
$scope task verify $end
$var reg 8 7 received_data [7:0] $end
$var reg 8 8 sent_data [7:0] $end
$upscope $end
$upscope $end
$enddefinitions $end
$comment Show the parameter values. $end
$dumpall
b10 0
b1 /
b0 .
b11 -
$end
#0
$dumpvars
bx 8
bx 7
b0 6
05
b0 4
b0 3
b0 2
b0 1
b0 ,
0+
0*
0)
bx (
b0 '
0&
1%
b0 $
0#
0"
0!
$end
#5000
1*
b0 7
b0 8
1&
#10000
0&
#15000
b1 3
1+
b11110000 (
b11110000 '
b11110000 ,
1&
#20000
0&
#25000
b10 3
b1 6
0+
1&
#30000
0&
#35000
b10 6
b11110000 4
0%
1&
#40000
0&
#45000
1)
b1 1
b11100000 4
1"
1!
15
1&
#50000
0&
#55000
0!
05
1&
#60000
0&
#65000
b1 $
b1 2
b10 1
b11000000 4
1!
15
1&
#70000
0&
#75000
0!
05
1&
#80000
0&
#85000
b11 $
b11 2
b11 1
b10000000 4
1!
15
1&
#90000
0&
#95000
0!
05
1&
#100000
0&
#105000
b111 $
b111 2
b100 1
b0 4
1!
15
1&
#110000
0&
#115000
0!
05
1&
#120000
0&
#125000
0)
b1111 $
b1111 2
b101 1
0"
1!
15
1&
#130000
0&
#135000
0!
05
1&
#140000
0&
#145000
b11110 $
b11110 2
b110 1
1!
15
1&
#150000
0&
#155000
0!
05
1&
#160000
0&
#165000
b111100 $
b111100 2
b111 1
1!
15
1&
#170000
0&
#175000
0!
05
1&
#180000
0&
#185000
b1111000 $
b1111000 2
b1000 1
1!
15
1&
#190000
0&
#195000
0!
05
1&
#200000
0&
#205000
b11 3
b11110000 $
b11110000 2
b1001 1
1!
15
1&
#210000
0&
#215000
b0 3
b11 6
0!
05
1&
#220000
0&
#225000
1#
1%
b0 6
1&
#230000
0&
#235000
b1 3
b0 $
b0 2
0#
1+
b1010101 (
b1010101 '
b1010101 ,
b11110000 7
b11110000 8
1&
#240000
0&
#245000
b10 3
b1 6
0+
1&
#250000
0&
#255000
b10 6
b0 1
b1010101 4
0%
1&
#260000
0&
#265000
b1 1
b10101010 4
1!
15
1&
#270000
0&
#275000
0!
05
1&
#280000
0&
#285000
1)
b10 1
b1010100 4
1"
1!
15
1&
#290000
0&
#295000
0!
05
1&
#300000
0&
#305000
0)
b1 $
b1 2
b11 1
b10101000 4
0"
1!
15
1&
#310000
0&
#315000
0!
05
1&
#320000
0&
#325000
1)
b10 $
b10 2
b100 1
b1010000 4
1"
1!
15
1&
#330000
0&
#335000
0!
05
1&
#340000
0&
#345000
0)
b101 $
b101 2
b101 1
b10100000 4
0"
1!
15
1&
#350000
0&
#355000
0!
05
1&
#360000
0&
#365000
1)
b1010 $
b1010 2
b110 1
b1000000 4
1"
1!
15
1&
#370000
0&
#375000
0!
05
1&
#380000
0&
#385000
0)
b10101 $
b10101 2
b111 1
b10000000 4
0"
1!
15
1&
#390000
0&
#395000
0!
05
1&
#400000
0&
#405000
1)
b101010 $
b101010 2
b1000 1
b0 4
1"
1!
15
1&
#410000
0&
#415000
0!
05
1&
#420000
0&
#425000
b11 3
0)
b1010101 $
b1010101 2
b1001 1
0"
1!
15
1&
#430000
0&
#435000
b0 3
b11 6
0!
05
1&
#440000
0&
#445000
1#
1%
b0 6
1&
#450000
0&
#455000
b0 $
b0 2
0#
b0 (
b10101010 '
b10101010 ,
b1010101 7
b1010101 8
1&
#460000
0&
#465000
b1 3
1+
b1111000 (
b1111000 '
b1111000 ,
b0 7
b0 8
1&
#470000
0&
#475000
b10 3
b1 6
0+
1&
#480000
0&
#485000
b0 1
b1111000 4
0%
b10 6
1&
#490000
0&
#495000
b1 1
b11110000 4
1!
15
1&
#500000
0&
#505000
0!
05
1&
#510000
0&
#515000
1)
b10 1
b11100000 4
1"
1!
15
1&
#520000
0&
#525000
0!
05
1&
#530000
0&
#535000
b1 $
b1 2
b11 1
b11000000 4
1!
15
1&
#540000
0&
#545000
0!
05
1&
#550000
0&
#555000
b11 $
b11 2
b100 1
b10000000 4
1!
15
1&
#560000
0&
#565000
0!
05
1&
#570000
0&
#575000
b111 $
b111 2
b101 1
b0 4
1!
15
1&
#580000
0&
#585000
0!
05
1&
#590000
0&
#595000
0)
b1111 $
b1111 2
b110 1
0"
1!
15
1&
#600000
0&
#605000
0!
05
1&
#610000
0&
#615000
b11110 $
b11110 2
b111 1
1!
15
1&
#620000
0&
#625000
0!
05
1&
#630000
0&
#635000
b111100 $
b111100 2
b1000 1
1!
15
1&
#640000
0&
#645000
0!
05
1&
#650000
0&
#655000
b11 3
b1111000 $
b1111000 2
b1001 1
1!
15
1&
#660000
0&
#665000
b0 3
0!
b11 6
05
1&
#670000
0&
#675000
b0 6
1#
1%
1&
#680000
0&
#685000
b1 3
b0 $
b0 2
0#
1+
b110011 (
b110011 '
b110011 ,
b1111000 7
b1111000 8
1&
#690000
0&
#695000
b10 3
b1 6
0+
1&
#700000
0&
#705000
b0 1
b110011 4
0%
b10 6
1&
#710000
0&
#715000
b1 1
b1100110 4
1!
15
1&
#720000
0&
#725000
0!
05
1&
#730000
0&
#735000
b10 1
b11001100 4
1!
15
1&
#740000
0&
#745000
0!
05
1&
#750000
0&
#755000
1)
b11 1
b10011000 4
1"
1!
15
1&
#760000
0&
#765000
0!
05
1&
#770000
0&
#775000
b1 $
b1 2
b100 1
b110000 4
1!
15
1&
#780000
0&
#785000
0!
05
1&
#790000
0&
#795000
0)
b11 $
b11 2
b101 1
b1100000 4
0"
1!
15
1&
#800000
0&
#805000
0!
05
1&
#810000
0&
#815000
b110 $
b110 2
b110 1
b11000000 4
1!
15
1&
#820000
0&
#825000
0!
05
1&
#830000
0&
#835000
1)
b1100 $
b1100 2
b111 1
b10000000 4
1"
1!
15
1&
#840000
0&
#845000
0!
05
1&
#850000
0&
#855000
b11001 $
b11001 2
b1000 1
b0 4
1!
15
1&
#860000
0&
#865000
0!
05
1&
#870000
0&
#875000
b11 3
0)
b110011 $
b110011 2
b1001 1
0"
1!
15
1&
#880000
0&
#885000
b0 3
0!
b11 6
05
1&
#890000
0&
#895000
b0 6
1#
1%
1&
#900000
0&
#905000
b0 $
b0 2
0#
b110011 7
b110011 8
1&
